lua2pack/__init__.py
lua2pack/lua_runtime.py
lua2pack/osdeps_utils.py
lua2pack/osdeps/__init__.py
lua2pack/osdeps/generic.py
lua2pack/osdeps/lua_rockspec.py
lua2pack/osdeps/obsinfo.py
lua2pack/templates/generic.spec
lua2pack/templates/obs.obsinfo
lua2pack/templates/rock.rockspec
lua2pack-1.1.0.dist-info/licenses/LICENSE
lua2pack-1.1.0.dist-info/METADATA
lua2pack-1.1.0.dist-info/WHEEL
lua2pack-1.1.0.dist-info/entry_points.txt
lua2pack-1.1.0.dist-info/top_level.txt
lua2pack-1.1.0.dist-info/RECORD
